LICENSE
README.md
setup.py
treasurykit/__init__.py
treasurykit/tax.py
treasurykit.egg-info/PKG-INFO
treasurykit.egg-info/SOURCES.txt
treasurykit.egg-info/dependency_links.txt
treasurykit.egg-info/requires.txt
treasurykit.egg-info/top_level.txt