Metadata-Version: 2.1
Name: treasurykit
Version: 1.1
Summary: Tools for finance and treasury specialists
Home-page: https://github.com/khorevkp/treasurykit
Author: Konstantin Khorev
Author-email: khorevkp@gmail.com
License: UNKNOWN
Platform: UNKNOWN
License-File: LICENSE
